blindfold/__init__.py
blindfold/blindfold.py
blindfold-1.0.0.dist-info/licenses/LICENSE
blindfold-1.0.0.dist-info/METADATA
blindfold-1.0.0.dist-info/WHEEL
blindfold-1.0.0.dist-info/top_level.txt
blindfold-1.0.0.dist-info/RECORD
