Metadata-Version: 2.4
Name: blindfold
Version: 1.0.0
Summary: Library for working with encrypted data within nilDB queries and replies.
License-Expression: MIT
Project-URL: Repository, https://github.com/nillionnetwork/blindfold-py
Project-URL: Documentation, https://blindfold.readthedocs.io
Requires-Python: >=3.9
License-File: LICENSE
Requires-Dist: parts~=4.0
Requires-Dist: hkdfs~=0.1
Requires-Dist: bcl~=3.0
Requires-Dist: shamirs~=4.0
Requires-Dist: pailliers<2.0.0,>=0.3.1
Provides-Extra: docs
Requires-Dist: toml~=0.10.2; extra == "docs"
Requires-Dist: sphinx~=7.4; extra == "docs"
Requires-Dist: sphinx-rtd-theme~=3.0; extra == "docs"
Requires-Dist: sphinx-autodoc-typehints~=2.3; extra == "docs"
Requires-Dist: pytest~=8.4; extra == "docs"
Provides-Extra: test
Requires-Dist: pytest~=8.4; extra == "test"
Requires-Dist: pytest-cov~=7.0; extra == "test"
Provides-Extra: lint
Requires-Dist: pylint~=3.3; extra == "lint"
Provides-Extra: coveralls
Requires-Dist: coveralls~=4.0; extra == "coveralls"
Provides-Extra: publish
Requires-Dist: build~=1.3; extra == "publish"
Requires-Dist: twine~=4.0; extra == "publish"
Dynamic: license-file
